{
	"npc_turret_ceiling": {
		"Offset": 0.0,
		"SpawnFlags": 32.0,
		"Class": "npc_turret_ceiling",
		"Category": "Combine",
		"OnCeiling": true,
		"Name": "#npc_turret_ceiling",
		"KeyValues": {
			"SquadName": "overwatch"
		}
	},
	"npc_dog": {
		"Category": "Humans + Resistance",
		"Name": "#npc_dog",
		"Class": "npc_dog"
	},
	"npc_gman": {
		"Category": "Humans + Resistance",
		"Name": "#npc_gman",
		"Class": "npc_gman"
	},
	"Refugee": {
		"Class": "npc_citizen",
		"Category": "Humans + Resistance",
		"Weapons": [
			"weapon_pistol",
			"weapon_smg1"
		],
		"Name": "#npc_citizen_refugee",
		"KeyValues": {
			"SquadName": "resistance",
			"citizentype": 2.0
		}
	},
	"npc_clawscanner": {
		"Offset": 20.0,
		"Class": "npc_clawscanner",
		"Category": "Combine",
		"KeyValues": {
			"SquadName": "overwatch"
		},
		"Name": "#npc_clawscanner",
		"NoDrop": true
	},
	"npc_citizen": {
		"Class": "npc_citizen",
		"Category": "Humans + Resistance",
		"Name": "#npc_citizen",
		"Weapons": [
			""
		],
		"KeyValues": {
			"SquadName": "resistance",
			"citizentype": 1.0
		}
	},
	"npc_turret_floor": {
		"TotalSpawnFlags": 0.0,
		"Offset": 2.0,
		"OnFloor": true,
		"Class": "npc_turret_floor",
		"Rotate": "{0 180 0}",
		"Category": "Combine",
		"Name": "#npc_turret_floor",
		"KeyValues": {
			"SquadName": "overwatch"
		}
	},
	"npc_turret_floor_resistance": {
		"TotalSpawnFlags": 0.0,
		"Offset": 2.0,
		"OnFloor": true,
		"Class": "npc_turret_floor",
		"Rotate": "{0 180 0}",
		"Category": "Humans + Resistance",
		"Name": "#npc_turret_floor_resistance",
		"KeyValues": {
			"SquadName": "overwatch",
			"SpawnFlags": 512.0
		}
	},
	"npc_headcrab": {
		"Category": "Zombies + Enemy Aliens",
		"Class": "npc_headcrab",
		"Name": "#npc_headcrab",
		"KeyValues": {
			"SquadName": "zombies"
		}
	},
	"npc_fastzombie_torso": {
		"Category": "Zombies + Enemy Aliens",
		"Class": "npc_fastzombie_torso",
		"Name": "#npc_fastzombie_torso",
		"KeyValues": {
			"SquadName": "zombies"
		}
	},
	"VortigauntUriah": {
		"Class": "npc_vortigaunt",
		"Category": "Humans + Resistance",
		"Name": "#npc_vortigaunt_uriah",
		"Model": "models/vortigaunt_doctor.mdl",
		"KeyValues": {
			"SquadName": "resistance"
		}
	},
	"npc_magnusson": {
		"Category": "Humans + Resistance",
		"Name": "#npc_magnusson",
		"Class": "npc_magnusson"
	},
	"npc_antlionguardian": {
		"Material": "Models/antlion_guard/antlionGuard2",
		"Class": "npc_antlionguard",
		"Category": "Zombies + Enemy Aliens",
		"Name": "#npc_antlionguardian",
		"KeyValues": {
			"cavernbreed": 1.0,
			"SquadName": "antlions",
			"incavern": 1.0
		}
	},
	"npc_fastzombie": {
		"Category": "Zombies + Enemy Aliens",
		"Class": "npc_fastzombie",
		"Name": "#npc_fastzombie",
		"KeyValues": {
			"SquadName": "zombies"
		}
	},
	"npc_security_camera": {
		"Offset": -1.0,
		"SnapToNormal": true,
		"Class": "npc_security_camera",
		"Category": "Portal",
		"SpawnFlags": 32.0,
		"Name": "#npc_security_camera",
		"NoDrop": true
	},
	"npc_kleiner": {
		"Category": "Humans + Resistance",
		"Name": "#npc_kleiner",
		"Class": "npc_kleiner"
	},
	"CombinePrison": {
		"Skin": 0.0,
		"Weapons": [
			"weapon_smg1",
			"weapon_ar2"
		],
		"Class": "npc_combine_s",
		"Category": "Combine",
		"Model": "models/combine_soldier_prisonguard.mdl",
		"Name": "#npc_combine_s_prison",
		"KeyValues": {
			"SquadName": "novaprospekt",
			"Numgrenades": 5.0
		}
	},
	"npc_barney": {
		"Class": "npc_barney",
		"Category": "Humans + Resistance",
		"Name": "#npc_barney",
		"Weapons": [
			"weapon_smg1",
			"weapon_shotgun",
			"weapon_ar2"
		],
		"KeyValues": {
			"SquadName": "resistance"
		}
	},
	"npc_hunter": {
		"Category": "Combine",
		"Class": "npc_hunter",
		"Name": "#npc_hunter",
		"KeyValues": {
			"SquadName": "overwatch"
		}
	},
	"npc_headcrab_fast": {
		"Category": "Zombies + Enemy Aliens",
		"Class": "npc_headcrab_fast",
		"Name": "#npc_headcrab_fast",
		"KeyValues": {
			"SquadName": "zombies"
		}
	},
	"ShotgunSoldier": {
		"Skin": 1.0,
		"Weapons": [
			"weapon_shotgun"
		],
		"Class": "npc_combine_s",
		"Category": "Combine",
		"Model": "models/combine_soldier.mdl",
		"Name": "#npc_combine_s_shotgun",
		"KeyValues": {
			"SquadName": "overwatch",
			"Numgrenades": 5.0
		}
	},
	"npc_monk": {
		"Category": "Animals",
		"Weapons": [
			"weapon_annabelle"
		],
		"Name": "#npc_monk",
		"Class": "npc_monk"
	},
	"npc_mossman": {
		"Category": "Humans + Resistance",
		"Name": "#npc_mossman",
		"Class": "npc_mossman"
	},
	"npc_antlionguard": {
		"Category": "Zombies + Enemy Aliens",
		"Class": "npc_antlionguard",
		"Name": "#npc_antlionguard",
		"KeyValues": {
			"SquadName": "antlions"
		}
	},
	"npc_seagull": {
		"Category": "Animals",
		"Class": "npc_seagull",
		"Name": "#npc_seagull",
		"NoDrop": true
	},
	"npc_zombie": {
		"Category": "Zombies + Enemy Aliens",
		"Class": "npc_zombie",
		"Name": "#npc_zombie",
		"KeyValues": {
			"SquadName": "zombies"
		}
	},
	"npc_barnacle": {
		"Offset": 2.0,
		"Class": "npc_barnacle",
		"Category": "Zombies + Enemy Aliens",
		"OnCeiling": true,
		"Name": "#npc_barnacle"
	},
	"npc_manhack": {
		"Class": "npc_manhack",
		"Category": "Combine",
		"NoDrop": true,
		"Name": "#npc_manhack",
		"KeyValues": {
			"SquadName": "overwatch"
		}
	},
	"npc_zombine": {
		"Category": "Zombies + Enemy Aliens",
		"Class": "npc_zombine",
		"Name": "#npc_zombine",
		"KeyValues": {
			"SquadName": "zombies"
		}
	},
	"npc_eli": {
		"Category": "Humans + Resistance",
		"Name": "#npc_eli",
		"Class": "npc_eli"
	},
	"npc_fisherman": {
		"Category": "Humans + Resistance",
		"Weapons": [
			"weapon_oldmanharpoon"
		],
		"Name": "#npc_fisherman",
		"Class": "npc_fisherman"
	},
	"npc_strider": {
		"Offset": 100.0,
		"Class": "npc_strider",
		"Category": "Combine",
		"Name": "#npc_strider",
		"KeyValues": {
			"SquadName": "overwatch"
		}
	},
	"npc_vortigaunt": {
		"Category": "Humans + Resistance",
		"Class": "npc_vortigaunt",
		"Name": "#npc_vortigaunt",
		"KeyValues": {
			"SquadName": "resistance"
		}
	},
	"npc_cscanner": {
		"Offset": 20.0,
		"Class": "npc_cscanner",
		"Category": "Combine",
		"KeyValues": {
			"SquadName": "overwatch"
		},
		"Name": "#npc_cscanner",
		"NoDrop": true
	},
	"npc_combine_camera": {
		"Offset": 2.0,
		"KeyValues": {
			"SquadName": "overwatch"
		},
		"Class": "npc_combine_camera",
		"Category": "Combine",
		"OnCeiling": true,
		"Name": "#npc_combine_camera",
		"NoDrop": true
	},
	"npc_combine_s": {
		"Skin": 0.0,
		"Weapons": [
			"weapon_smg1",
			"weapon_ar2"
		],
		"Class": "npc_combine_s",
		"Category": "Combine",
		"Model": "models/combine_soldier.mdl",
		"Name": "#npc_combine_s",
		"KeyValues": {
			"SquadName": "overwatch",
			"Numgrenades": 5.0
		}
	},
	"npc_stalker": {
		"Offset": 10.0,
		"Class": "npc_stalker",
		"Category": "Combine",
		"Name": "#npc_stalker",
		"KeyValues": {
			"squadname": "npc_stalker_squad"
		}
	},
	"npc_helicopter": {
		"Offset": 300.0,
		"KeyValues": {
			"SquadName": "overwatch"
		},
		"Class": "npc_helicopter",
		"Category": "Combine",
		"Health": 600.0,
		"Name": "#npc_helicopter",
		"NoDrop": true
	},
	"npc_alyx": {
		"Class": "npc_alyx",
		"Category": "Humans + Resistance",
		"Name": "#npc_alyx",
		"Weapons": [
			"weapon_alyxgun",
			"weapon_smg1",
			"weapon_shotgun"
		],
		"KeyValues": {
			"SquadName": "resistance"
		}
	},
	"npc_antlion": {
		"Category": "Zombies + Enemy Aliens",
		"Class": "npc_antlion",
		"Name": "#npc_antlion",
		"KeyValues": {
			"SquadName": "antlions"
		}
	},
	"npc_antlion_grub": {
		"Offset": 1.0,
		"Class": "npc_antlion_grub",
		"Category": "Zombies + Enemy Aliens",
		"Name": "#npc_antlion_grub",
		"NoDrop": true
	},
	"Medic": {
		"SpawnFlags": 131080.0,
		"Class": "npc_citizen",
		"Category": "Humans + Resistance",
		"Name": "#npc_citizen_medic",
		"Weapons": [
			"weapon_pistol",
			"weapon_smg1",
			"weapon_ar2",
			"weapon_shotgun"
		],
		"KeyValues": {
			"SquadName": "resistance",
			"citizentype": 3.0
		}
	},
	"npc_combinedropship": {
		"Offset": 300.0,
		"Class": "npc_combinedropship",
		"Category": "Combine",
		"KeyValues": {
			"SquadName": "overwatch"
		},
		"Name": "#npc_combinedropship",
		"NoDrop": true
	},
	"CombineElite": {
		"KeyValues": {
			"Numgrenades": 10.0,
			"SquadName": "overwatch"
		},
		"Skin": 0.0,
		"Model": "models/combine_super_soldier.mdl",
		"Class": "npc_combine_s",
		"Category": "Combine",
		"Weapons": [
			"weapon_ar2"
		],
		"Name": "#npc_combine_s_elite",
		"SpawnFlags": 16384.0
	},
	"npc_crow": {
		"Category": "Animals",
		"Class": "npc_crow",
		"Name": "#npc_crow",
		"NoDrop": true
	},
	"npc_rocket_turret": {
		"Offset": 0.0,
		"SpawnFlags": 2.0,
		"Class": "npc_rocket_turret",
		"Category": "Portal",
		"Rotate": "{0 180 0}",
		"Name": "#npc_rocket_turret",
		"OnFloor": true
	},
	"npc_metropolice": {
		"SpawnFlags": 8.0,
		"Class": "npc_metropolice",
		"Category": "Combine",
		"Weapons": [
			"weapon_stunstick",
			"weapon_pistol",
			"weapon_smg1"
		],
		"Name": "#npc_metropolice",
		"KeyValues": {
			"SquadName": "overwatch"
		}
	},
	"Rebel": {
		"SpawnFlags": 262144.0,
		"Class": "npc_citizen",
		"Category": "Humans + Resistance",
		"Name": "#npc_citizen_rebel",
		"Weapons": [
			"weapon_pistol",
			"weapon_ar2",
			"weapon_smg1",
			"weapon_ar2",
			"weapon_shotgun"
		],
		"KeyValues": {
			"SquadName": "resistance",
			"citizentype": 3.0
		}
	},
	"npc_tf2_ghost": {
		"Category": "Nextbot",
		"Name": "Example NPC",
		"Class": "npc_tf2_ghost"
	},
	"npc_poisonzombie": {
		"Category": "Zombies + Enemy Aliens",
		"Class": "npc_poisonzombie",
		"Name": "#npc_poisonzombie",
		"KeyValues": {
			"SquadName": "poison"
		}
	},
	"npc_combinegunship": {
		"Offset": 300.0,
		"Class": "npc_combinegunship",
		"Category": "Combine",
		"KeyValues": {
			"SquadName": "overwatch"
		},
		"Name": "#npc_combinegunship",
		"NoDrop": true
	},
	"PrisonShotgunner": {
		"Skin": 1.0,
		"Weapons": [
			"weapon_shotgun"
		],
		"Class": "npc_combine_s",
		"Category": "Combine",
		"Model": "models/combine_soldier_prisonguard.mdl",
		"Name": "#npc_combine_s_prison_shotgun",
		"KeyValues": {
			"SquadName": "novaprospekt",
			"Numgrenades": 5.0
		}
	},
	"npc_pigeon": {
		"Category": "Animals",
		"Class": "npc_pigeon",
		"Name": "#npc_pigeon",
		"NoDrop": true
	},
	"npc_antlion_worker": {
		"Category": "Zombies + Enemy Aliens",
		"Class": "npc_antlion_worker",
		"Name": "#npc_antlion_worker",
		"KeyValues": {
			"SquadName": "antlions"
		}
	},
	"npc_headcrab_black": {
		"Category": "Zombies + Enemy Aliens",
		"Class": "npc_headcrab_black",
		"Name": "#npc_headcrab_black",
		"KeyValues": {
			"SquadName": "poison"
		}
	},
	"npc_odessa": {
		"Name": "#npc_odessa",
		"Class": "npc_citizen",
		"Category": "Humans + Resistance",
		"Model": "models/odessa.mdl",
		"Weapons": [
			""
		],
		"KeyValues": {
			"SquadName": "resistance",
			"citizentype": 4.0
		}
	},
	"npc_breen": {
		"Category": "Humans + Resistance",
		"Name": "#npc_breen",
		"Class": "npc_breen"
	},
	"npc_rollermine": {
		"Offset": 20.0,
		"Class": "npc_rollermine",
		"Category": "Combine",
		"KeyValues": {
			"SquadName": "overwatch"
		},
		"Name": "#npc_rollermine",
		"NoDrop": true
	},
	"npc_zombie_torso": {
		"Category": "Zombies + Enemy Aliens",
		"Class": "npc_zombie_torso",
		"Name": "#npc_zombie_torso",
		"KeyValues": {
			"SquadName": "zombies"
		}
	},
	"npc_portal_turret_floor": {
		"TotalSpawnFlags": 0.0,
		"Offset": 2.0,
		"Class": "npc_portal_turret_floor",
		"Category": "Portal",
		"Rotate": "{0 180 0}",
		"Name": "#npc_portal_turret_floor",
		"OnFloor": true
	},
	"VortigauntSlave": {
		"Category": "Humans + Resistance",
		"Name": "#npc_vortigaunt_slave",
		"Model": "models/vortigaunt_slave.mdl",
		"Class": "npc_vortigaunt"
	}
}
